copilotagent/__init__.py
copilotagent/blend_connect.py
copilotagent/cloud_subagents.py
copilotagent/encompass_connect.py
copilotagent/graph.py
copilotagent/landingai_client.py
copilotagent/py.typed
copilotagent/middleware/__init__.py
copilotagent/middleware/dynamic_tools.py
copilotagent/middleware/filesystem.py
copilotagent/middleware/initial_message.py
copilotagent/middleware/patch_tool_calls.py
copilotagent/middleware/planning.py
copilotagent/middleware/server_middleware.py
copilotagent/middleware/station_middleware.py
copilotagent/middleware/subagents.py
copilotagent-0.1.28.dist-info/licenses/LICENSE
copilotagent-0.1.28.dist-info/METADATA
copilotagent-0.1.28.dist-info/WHEEL
copilotagent-0.1.28.dist-info/top_level.txt
copilotagent-0.1.28.dist-info/RECORD
