Metadata-Version: 2.4
Name: copilotagent
Version: 0.1.28
Summary: General purpose 'deep agent' with sub-agent spawning, todo list capabilities, and mock file system. Built on LangGraph.
License-Expression: MIT
Requires-Python: <4.0,>=3.11
License-File: LICENSE
Requires-Dist: langchain-anthropic<2.0.0,>=1.0.0
Requires-Dist: langchain<2.0.0,>=1.0.0
Requires-Dist: langchain-core<2.0.0,>=1.0.0
Requires-Dist: langgraph-sdk<1.0.0,>=0.1.0
Requires-Dist: requests<3.0.0,>=2.31.0
Requires-Dist: cuteagent>=0.2.24
Provides-Extra: dev
Requires-Dist: pytest; extra == "dev"
Requires-Dist: pytest-cov; extra == "dev"
Requires-Dist: build; extra == "dev"
Requires-Dist: twine; extra == "dev"
Requires-Dist: langchain-openai; extra == "dev"
Provides-Extra: hitl
Requires-Dist: cuteagent>=0.2.24; extra == "hitl"
Dynamic: license-file
